langchain_moxe/__init__.py
langchain_moxe/chat_models.py
langchain_moxe/client.py
langchain_moxe/embeddings.py
langchain_moxe/inference.py
langchain_moxe/llms.py
langchain_moxe/py.typed
langchain_moxe/utils.py
langchain_moxe-0.1.2.dist-info/licenses/LICENSE
langchain_moxe-0.1.2.dist-info/METADATA
langchain_moxe-0.1.2.dist-info/WHEEL
langchain_moxe-0.1.2.dist-info/top_level.txt
langchain_moxe-0.1.2.dist-info/RECORD
